persian_telegram_bot_calendar-1.1.1.dist-info/licenses/LICENSE.txt
telegram_bot_calendar/__init__.py
telegram_bot_calendar/base.py
telegram_bot_calendar/detailed.py
telegram_bot_calendar/static.py
telegram_bot_calendar/wmonth.py
telegram_bot_calendar/wyear.py
persian_telegram_bot_calendar-1.1.1.dist-info/METADATA
persian_telegram_bot_calendar-1.1.1.dist-info/WHEEL
persian_telegram_bot_calendar-1.1.1.dist-info/top_level.txt
persian_telegram_bot_calendar-1.1.1.dist-info/RECORD
