Metadata-Version: 2.4
Name: persian-telegram-bot-calendar
Version: 1.1.1
Summary: Python inline calendar for telegram bots with persian jalali date support
Home-page: https://github.com/mbhesam/python-telegram-bot-calendar
Download-URL: https://github.com/mbhesam/python-telegram-bot-calendar/archive/v_1.1.1.tar.gz
Author: Artem Bakhanov - Mohammad
Author-email: artembakhanov@gmail.com
License: MIT
Keywords: calendar,persian calendar,telegram,bot,telegram bot
Classifier: Development Status :: 4 - Beta
Classifier: Intended Audience :: Developers
Classifier: License :: OSI Approved :: MIT License
Classifier: Programming Language :: Python :: 3
Classifier: Programming Language :: Python :: 3.4
Classifier: Programming Language :: Python :: 3.5
Classifier: Programming Language :: Python :: 3.6
Classifier: Programming Language :: Python :: 3.6
Classifier: Programming Language :: Python :: 3.7
Classifier: Programming Language :: Python :: 3.8
Classifier: Programming Language :: Python :: 3.9
Classifier: Programming Language :: Python :: 3.10
Classifier: Programming Language :: Python :: 3.11
Classifier: Programming Language :: Python :: 3.12
License-File: LICENSE.txt
Requires-Dist: python-dateutil
Requires-Dist: jdatetime
Provides-Extra: telethon
Requires-Dist: telethon; extra == "telethon"
Dynamic: author
Dynamic: author-email
Dynamic: classifier
Dynamic: description
Dynamic: description-content-type
Dynamic: download-url
Dynamic: home-page
Dynamic: keywords
Dynamic: license
Dynamic: license-file
Dynamic: provides-extra
Dynamic: requires-dist
Dynamic: summary
